dummy_problems/__init__.py
dummy_problems/dataloaders/__init__.py
dummy_problems/dataloaders/core.py
dummy_problems/models/core.py
dummy_problems-0.1.1.dist-info/METADATA
dummy_problems-0.1.1.dist-info/WHEEL
dummy_problems-0.1.1.dist-info/RECORD
