Metadata-Version: 2.1
Name: dummy-problems
Version: 0.1.1
Summary: Solving simple problems using machine learning
Home-page: https://github.com/jmariscal-harana/dummy-problems
Author: Jorge Mariscal Harana
Author-email: jorge.mariscal.harana@gmail.com
Requires-Python: >=3.10,<4.0
Classifier: Programming Language :: Python :: 3
Classifier: Programming Language :: Python :: 3.10
Classifier: Programming Language :: Python :: 3.11
Classifier: Programming Language :: Python :: 3.12
Classifier: Programming Language :: Python :: 3.13
Requires-Dist: lightning (>=2.5.0.post0,<3.0.0)
Project-URL: Repository, https://github.com/jmariscal-harana/dummy-problems
